lucagplm/__init__.py
lucagplm/configuration_lucagplm.py
lucagplm/convert_model.py
lucagplm/modeling_lucagplm.py
lucagplm/tokenization_lucagplm.py
lucagplm-1.1.4.dist-info/licenses/LICENSE
lucagplm-1.1.4.dist-info/METADATA
lucagplm-1.1.4.dist-info/WHEEL
lucagplm-1.1.4.dist-info/entry_points.txt
lucagplm-1.1.4.dist-info/top_level.txt
lucagplm-1.1.4.dist-info/RECORD
