Metadata-Version: 2.4
Name: lucagplm
Version: 1.1.4
Summary: LucaGPLM - The LUCA general purpose language model.
Author-email: Yuan-Fei Pan <yfpan16@gmail.com>, Yong He <sanyuan.hy@alibaba-inc.com>
Project-URL: Homepage, https://github.com/LucaOne/LucaOne
Project-URL: Issues, https://github.com/LucaOne/LucaOne/issues
Classifier: Programming Language :: Python :: 3
Classifier: Operating System :: OS Independent
Requires-Python: >=3.9
License-File: LICENSE
Requires-Dist: torch
Requires-Dist: transformers
Dynamic: license-file
